pydiagral/__init__.py
pydiagral/api.py
pydiagral/constants.py
pydiagral/exceptions.py
pydiagral/models.py
pydiagral/utils.py
pydiagral-1.6.0.dist-info/METADATA
pydiagral-1.6.0.dist-info/WHEEL
pydiagral-1.6.0.dist-info/licenses/LICENSE
pydiagral-1.6.0.dist-info/RECORD
