Metadata-Version: 2.4
Name: pydiagral
Version: 1.6.0
Summary: A Python library for interacting with Diagral systems
Project-URL: Homepage, https://github.com/mguyard/pydiagral
Project-URL: Documentation, https://github.com/mguyard/pydiagral
Project-URL: Repository, https://github.com/mguyard/pydiagral.git
Project-URL: Issues, https://github.com/mguyard/pydiagral/issues
Project-URL: Changelog, https://github.com/mguyard/pydiagral/blob/main/CHANGELOG.md
Author: Marc Guyard
Maintainer: Marc Guyard
License:                     GNU GENERAL PUBLIC LICENSE
License-File: LICENSE
Keywords: diagral,home automation,python
Classifier: Development Status :: 5 - Production/Stable
Classifier: Intended Audience :: Developers
Classifier: License :: OSI Approved :: GNU General Public License v3 or later (GPLv3+)
Classifier: Operating System :: OS Independent
Classifier: Programming Language :: Python :: 3
Classifier: Topic :: Security
Requires-Python: >=3.10
Requires-Dist: aiohttp<4.0.0,>=3.8.0
Provides-Extra: dev
Requires-Dist: pytest; extra == 'dev'
Requires-Dist: pytest-asyncio; extra == 'dev'
Requires-Dist: python-dotenv; extra == 'dev'
